README.md
setup.py
metadb/__init__.py
metadb/test_db.py
metadb/utils.py
metadb.egg-info/PKG-INFO
metadb.egg-info/SOURCES.txt
metadb.egg-info/dependency_links.txt
metadb.egg-info/not-zip-safe
metadb.egg-info/requires.txt
metadb.egg-info/top_level.txt