Metadata-Version: 2.1
Name: metadb
Version: 0.0.1
Summary: A pattern of types theory to mongodb.
Home-page: https://gitlab.com/wefindx/metadb
Author: Mindey
Author-email: mindey@qq.com
License: ASK FOR PERMISSIONS
Platform: UNKNOWN
Provides-Extra: test
